lib_test_pip_samir539/__init__.py
lib_test_pip_samir539/addition.py
lib_test_pip_samir539/multiplication.py
lib_test_pip_samir539/print_stuff.py
lib_test_pip_samir539-0.0.7.dist-info/METADATA
lib_test_pip_samir539-0.0.7.dist-info/WHEEL
lib_test_pip_samir539-0.0.7.dist-info/RECORD
