Metadata-Version: 2.3
Name: lib_test_pip_samir539
Version: 0.0.7
Summary: basic math lib
Project-URL: Homepage, https://github.com/samir539/lib_test_pip
Classifier: License :: OSI Approved :: MIT License
Classifier: Operating System :: OS Independent
Classifier: Programming Language :: Python :: 3
Requires-Python: >=3.8
